[
  {
    "name": "Downtown Las Vegas",
    "id": "1",
    "geometry": {
      "type": "FeatureCollection",
      "features": [
        {
          "type": "Feature",
          "properties": {},
          "geometry": {
            "type": "Polygon",
            "coordinates": [
              [
                [
                  -115.17731666564941,
                  36.13707757019889
                ],
                [
                  -115.17319679260252,
                  36.13706024080007
                ],
                [
                  -115.17502069473267,
                  36.13420083758107
                ],
                [
                  -115.17244577407837,
                  36.134235497637846
                ],
                [
                  -115.16609430313109,
                  36.144009022771975
                ],
                [
                  -115.15583753585817,
                  36.143645136743245
                ],
                [
                  -115.14620304107665,
                  36.158805624457074
                ],
                [
                  -115.11893033981322,
                  36.15884027364331
                ],
                [
                  -115.11882305145264,
                  36.1592387381841
                ],
                [
                  -115.11781454086304,
                  36.16048609234975
                ],
                [
                  -115.1162052154541,
                  36.161248354570134
                ],
                [
                  -115.11590480804442,
                  36.16247835297856
                ],
                [
                  -115.11590480804442,
                  36.16788318766737
                ],
                [
                  -115.12294292449951,
                  36.16781389727332
                ],
                [
                  -115.12455224990845,
                  36.16803909083007
                ],
                [
                  -115.12631177902222,
                  36.16855876579924
                ],
                [
                  -115.13667583465576,
                  36.17332229245195
                ],
                [
                  -115.1388430595398,
                  36.173911217452954
                ],
                [
                  -115.14066696166992,
                  36.174292284212704
                ],
                [
                  -115.14339208602905,
                  36.17531422682836
                ],
                [
                  -115.14553785324097,
                  36.17559136151155
                ],
                [
                  -115.14699697494507,
                  36.175487436120235
                ],
                [
                  -115.15120267868043,
                  36.17436156887901
                ],
                [
                  -115.15444278717041,
                  36.17304514974349
                ],
                [
                  -115.15731811523436,
                  36.17153816911135
                ],
                [
                  -115.15894889831543,
                  36.16873199002325
                ],
                [
                  -115.16002178192137,
                  36.1653713717453
                ],
                [
                  -115.16025781631468,
                  36.162530324317366
                ],
                [
                  -115.16034364700316,
                  36.15849378109213
                ],
                [
                  -115.16053676605223,
                  36.15660536977439
                ],
                [
                  -115.16154527664183,
                  36.15513272388132
                ],
                [
                  -115.16454935073853,
                  36.15173687028867
                ],
                [
                  -115.16817569732666,
                  36.14766511728071
                ],
                [
                  -115.17731666564941,
                  36.13707757019889
                ]
              ]
            ]
          }
        }
      ]
    }
  },
  {
    "name": "Summerlin",
    "id": 2,
    "geometry": {
      "type": "FeatureCollection",
      "features": [
        {
          "type": "Feature",
          "properties": {},
          "geometry": {
            "type": "Polygon",
            "coordinates": [
              [
                [
                  -115.33423662185669,
                  36.220128016503246
                ],
                [
                  -115.3250741958618,
                  36.21834495940409
                ],
                [
                  -115.27872562408447,
                  36.21857000768672
                ],
                [
                  -115.27902603149413,
                  36.20466773339572
                ],
                [
                  -115.27932643890381,
                  36.203542285580326
                ],
                [
                  -115.27979850769044,
                  36.20260728585832
                ],
                [
                  -115.28112888336183,
                  36.20111818917014
                ],
                [
                  -115.28235197067261,
                  36.19976758860748
                ],
                [
                  -115.28005599975586,
                  36.19838233305598
                ],
                [
                  -115.27683734893799,
                  36.19723947877367
                ],
                [
                  -115.27424097061157,
                  36.19682389126203
                ],
                [
                  -115.27166604995728,
                  36.19685852363892
                ],
                [
                  -115.26887655258177,
                  36.19718753045534
                ],
                [
                  -115.26660203933716,
                  36.19720484656526
                ],
                [
                  -115.26469230651857,
                  36.19694510451414
                ],
                [
                  -115.26164531707764,
                  36.19614855685075
                ],
                [
                  -115.26037931442262,
                  36.1960966078086
                ],
                [
                  -115.2601647377014,
                  36.18880608375461
                ],
                [
                  -115.28756618499754,
                  36.188598267894115
                ],
                [
                  -115.28700828552248,
                  36.17018705838945
                ],
                [
                  -115.31550407409668,
                  36.17010044793334
                ],
                [
                  -115.3140664100647,
                  36.158978870234996
                ],
                [
                  -115.35764694213867,
                  36.159048168438986
                ],
                [
                  -115.36453485488892,
                  36.153954587253416
                ],
                [
                  -115.3952407836914,
                  36.15366005033071
                ],
                [
                  -115.40386676788329,
                  36.16166413083919
                ],
                [
                  -115.41363000869752,
                  36.16786586507461
                ],
                [
                  -115.41465997695923,
                  36.19460738727727
                ],
                [
                  -115.40315866470337,
                  36.194780553910626
                ],
                [
                  -115.4029870033264,
                  36.21303016949126
                ],
                [
                  -115.37453413009644,
                  36.21308210729577
                ],
                [
                  -115.3745985031128,
                  36.22024919366622
                ],
                [
                  -115.33423662185669,
                  36.220128016503246
                ]
              ]
            ]
          }
        }
      ]
    }
  }

]
